dsgl/__init__.py
dsgl/aws_utils.py
dsgl/cli.py
dsgl/core.py
dsgl/models.py
dsgl/utils.py
dsgl-0.2.0.dist-info/METADATA
dsgl-0.2.0.dist-info/WHEEL
dsgl-0.2.0.dist-info/entry_points.txt
dsgl-0.2.0.dist-info/top_level.txt
dsgl-0.2.0.dist-info/RECORD
