Metadata-Version: 2.1
Name: dsgl
Version: 0.2.0
Summary: Library consisting of DS shortcuts and best practice functions for the Globallogic Datascience team
Home-page: UNKNOWN
Author: DS GL Team
License: MIT
Keywords: python,data,science,globallogic
Platform: UNKNOWN
